strengthtrainingtoolkit/__init__.py
strengthtrainingtoolkit/__main__.py
strengthtrainingtoolkit/__version__.py
strengthtrainingtoolkit/cli.py
strengthtrainingtoolkit/database.py
strengthtrainingtoolkit/planning.py
strengthtrainingtoolkit-0.2.0.dist-info/AUTHORS.rst
strengthtrainingtoolkit-0.2.0.dist-info/LICENSE
strengthtrainingtoolkit-0.2.0.dist-info/METADATA
strengthtrainingtoolkit-0.2.0.dist-info/WHEEL
strengthtrainingtoolkit-0.2.0.dist-info/entry_points.txt
strengthtrainingtoolkit-0.2.0.dist-info/top_level.txt
strengthtrainingtoolkit-0.2.0.dist-info/RECORD
