Metadata-Version: 2.1
Name: strengthtrainingtoolkit
Version: 0.2.0
Summary: Timo's Strength Training Toolkit. Grow strong!
Home-page: https://github.com/tim00w/python-strength-training-toolkit
Author: Timo Lesterhuis
Author-email: TimoLesterhuis@gmail.com
License: MIT license
Platform: UNKNOWN
Classifier: Development Status :: 5 - Production/Stable
Classifier: Intended Audience :: Developers
Classifier: License :: OSI Approved :: MIT License
Classifier: Operating System :: Unix
Classifier: Operating System :: POSIX
Classifier: Operating System :: Microsoft :: Windows
Classifier: Programming Language :: Python
Classifier: Programming Language :: Python :: 3
Classifier: Programming Language :: Python :: 3.6
Classifier: Programming Language :: Python :: 3.7
Classifier: Programming Language :: Python :: Implementation :: CPython
Classifier: Programming Language :: Python :: Implementation :: PyPy
Classifier: Topic :: Utilities
Requires-Dist: click
Requires-Dist: streprogen
Requires-Dist: sqlalchemy
